ccrawl/__init__.py
ccrawl/conf.py
ccrawl/core.py
ccrawl/db.py
ccrawl/graphs.py
ccrawl/main.py
ccrawl/parser.py
ccrawl/utils.py
ccrawl/ext/__init__.py
ccrawl/ext/amoco.py
ccrawl/ext/ctypes_.py
ccrawl/ext/ghidra.py
ccrawl/ext/ghidra_.py
ccrawl/ext/ida.py
ccrawl/formatters/C.py
ccrawl/formatters/__init__.py
ccrawl/formatters/amoco.py
ccrawl/formatters/ctypes_.py
ccrawl/formatters/raw.py
ccrawl/formatters/volatility.py
ccrawl/srv/__init__.py
ccrawl/srv/main.py
ccrawl-1.9.dist-info/LICENSE
ccrawl-1.9.dist-info/METADATA
ccrawl-1.9.dist-info/WHEEL
ccrawl-1.9.dist-info/entry_points.txt
ccrawl-1.9.dist-info/top_level.txt
ccrawl-1.9.dist-info/RECORD
